watchmen_model/__init__.py
watchmen_model/admin/__init__.py
watchmen_model/admin/conditional.py
watchmen_model/admin/enumeration.py
watchmen_model/admin/factor.py
watchmen_model/admin/pipeline.py
watchmen_model/admin/pipeline_action.py
watchmen_model/admin/pipeline_action_delete.py
watchmen_model/admin/pipeline_action_read.py
watchmen_model/admin/pipeline_action_system.py
watchmen_model/admin/pipeline_action_write.py
watchmen_model/admin/pipeline_graphic.py
watchmen_model/admin/space.py
watchmen_model/admin/topic.py
watchmen_model/admin/topic_snapshot.py
watchmen_model/admin/user.py
watchmen_model/admin/user_group.py
watchmen_model/analysis/__init__.py
watchmen_model/analysis/factor_index.py
watchmen_model/analysis/pipeline_index.py
watchmen_model/chart/__init__.py
watchmen_model/chart/chart.py
watchmen_model/chart/chart_basic_structure.py
watchmen_model/chart/chart_basic_style.py
watchmen_model/chart/chart_enums.py
watchmen_model/chart/chart_settings.py
watchmen_model/chart/chart_types.py
watchmen_model/common/__init__.py
watchmen_model/common/data_result_set.py
watchmen_model/common/graphic.py
watchmen_model/common/model.py
watchmen_model/common/pagination.py
watchmen_model/common/parameter_and_condition.py
watchmen_model/common/storable.py
watchmen_model/common/tuple.py
watchmen_model/common/tuple_ids.py
watchmen_model/console/__init__.py
watchmen_model/console/connected_space.py
watchmen_model/console/connected_space_graphic.py
watchmen_model/console/dashboard.py
watchmen_model/console/data_result_set.py
watchmen_model/console/report.py
watchmen_model/console/subject.py
watchmen_model/console/subject_ext.py
watchmen_model/console/utils.py
watchmen_model/dqc/__init__.py
watchmen_model/dqc/catalog.py
watchmen_model/dqc/dqc_pipelines.py
watchmen_model/dqc/dqc_topics.py
watchmen_model/dqc/monitor_data.py
watchmen_model/dqc/monitor_job_lock.py
watchmen_model/dqc/monitor_result.py
watchmen_model/dqc/monitor_rule.py
watchmen_model/dqc/topic_profile.py
watchmen_model-18.0.1.dist-info/METADATA
watchmen_model-18.0.1.dist-info/WHEEL
watchmen_model-18.0.1.dist-info/licenses/LICENSE
watchmen_model-18.0.1.dist-info/RECORD
